pytracekit-0.1.1.dist-info/METADATA
pytracekit-0.1.1.dist-info/WHEEL
pytracekit/__init__.py
pytracekit/config/TraceConfig.py
pytracekit/constants/common.py
pytracekit/decorators/__init__.py
pytracekit/decorators/tracing.py
pytracekit/instrumentors/__init__.py
pytracekit/instrumentors/base.py
pytracekit/instrumentors/falcon.py
pytracekit/instrumentors/fastapi.py
pytracekit/instrumentors/flask.py
pytracekit/instrumentors/utils.py
pytracekit/main.py
pytracekit/utils/__init__.py
pytracekit/utils/detect_framework.py
pytracekit/utils/trace_logger.py
pytracekit-0.1.1.dist-info/RECORD
