Metadata-Version: 2.1
Name: pytracekit
Version: 0.1.1
Summary: Distributed tracing made easy for python
Author-Email: Himanshu Barak <himanshu.barak12@gmail.com>
License: MIT
Requires-Python: >=3.9
Requires-Dist: opentelemetry-api>=1.23.0
Requires-Dist: opentelemetry-sdk>=1.23.0
Requires-Dist: opentelemetry-instrumentation-fastapi>=0.44b0
Requires-Dist: opentelemetry-instrumentation-pymongo>=0.44b0
Requires-Dist: opentelemetry-instrumentation-redis>=0.44b0
Requires-Dist: opentelemetry-exporter-otlp>=1.23.0
Requires-Dist: opentelemetry-instrumentation-requests>=0.44b0
Requires-Dist: redis>=5.0.3
Requires-Dist: pymongo>=4.6.3
Requires-Dist: opentelemetry-instrumentation-flask>=0.44b0
Requires-Dist: opentelemetry-instrumentation-falcon>=0.44b0
Requires-Dist: pytest>=8.1.1
